regression_lamia/__init__.py
regression_lamia/regression.py
regression_lamia-1.0.0.dist-info/LICENSE.txt
regression_lamia-1.0.0.dist-info/METADATA
regression_lamia-1.0.0.dist-info/WHEEL
regression_lamia-1.0.0.dist-info/top_level.txt
regression_lamia-1.0.0.dist-info/RECORD
