Metadata-Version: 2.1
Name: regression_lamia
Version: 1.0.0
Summary: An awesome package that does something
Home-page: http://pypi.python.org/pypi/regression_lamia/
Author: lamia
Author-email: l.abdelmalek@esi-sba.dz
License: LICENSE.txt
License-File: LICENSE.txt
Requires-Dist: regression-lamia
